Workbook

Sheet 价格指数
A1: =[1]!edb() -> Wind
A2: 指标名称 | B2: CPI:当月同比 | C2: CPI:环比 | D2: RPI:当月同比 | E2: RPI:环比 | F2: PPI:全部工业品:当月同比 | G2: PPI:全部工业品:环比
A3: 36922 | B3: 1.2 | C3: 0.9 | D3: -0.5 | E3: 0 | F3: 1.43 | G3: 0
A4: 36950 | B4: 0 | C4: 0.1 | D4: -1.7 | E4: 0 | F4: 0.9 | G4: 0
A5: 36981 | B5: 0.8 | C5: -0.6 | D5: -0.9 | E5: 0 | F5: 0.2 | G5: 0
A6: 37011 | B6: 1.6 | C6: 0.2 | D6: 0.1 | E6: 0 | F6: -0.1 | G6: 0
A7: 37042 | B7: 1.7 | C7: -0.5 | D7: 0.1 | E7: 0 | F7: -0.2 | G7: 0
A8: 37072 | B8: 1.4 | C8: -1.2 | D8: -0.1 | E8: 0 | F8: -0.6 | G8: 0
A9: 37103 | B9: 1.5 | C9: -0.5 | D9: -0.2 | E9: 0 | F9: -1.3 | G9: 0
A10: 37134 | B10: 1 | C10: 0.1 | D10: -1.2 | E10: 0 | F10: -2 | G10: 0
A11: 37164 | B11: -0.1 | C11: 0.9 | D11: -1.3 | E11: 0 | F11: -2.9 | G11: 0
A12: 37195 | B12: 0.2 | C12: 0.3 | D12: -0.8 | E12: 0 | F12: -3.1 | G12: 0
A13: 37225 | B13: -0.3 | C13: -0.2 | D13: -1.7 | E13: 0 | F13: -3.7 | G13: 0
A14: 37256 | B14: -0.3 | C14: 0.1 | D14: -1.8 | E14: 0 | F14: -4 | G14: 0
... A294: 45777 | B294: -0.1 | C294: 0.1 | D294: 0 | E294: 0 | F294: -2.7 | G294: -0.4

Sheet EDB
A1: =[1]!edb() -> Wind
A2: 指标名称 | B2: GDP:不变价:当季同比 | C2: 中金CMI指数:初值 | D2: 中金CMI指数:终值 | E2: 宏观经济景气指数:一致指数 | F2: PMI:新订单-产成品库存 | G2: 非制造业PMI:新订单 | H2: 社会消费品零售总额:当月同比 | I2: GDP:平减指数:GDP:初步核算:当季同比 | J2: CPI:当月同比 | K2: PPI:全部工业品:当月同比 | L2: RPI:当月同比 | M2: PPIRM:当月同比 | N2: M1:同比 | O2: M2:同比 | P2: 社会融资规模存量:同比 | Q2: 其他存款性公司:总资产:同比 | R2: 金融机构:本外币:资金运用:总计:同比 | S2: 社会融资规模:累计值 | T2: 社会融资规模存量 | U2: 工业增加值:当月同比 | V2: 工业增加值:环比:季调 | W2: 工业增加值:定基指数 | X2: M1 | Y2: M2 | Z2: PMI:新订单 | AA2: PMI:产成品库存
A3: 时间区间 | B3: 1992-03:2025-03 | C3: 2009-01:2025-04 | D3: 2009-01:2025-03 | E3: 1991-01:2024-11 | F3: 2005-01:2025-04 | G3: 2007-01:2025-04 | H3: 1995-01:2025-03 | I3: 1993-03:2025-03 | J3: 1987-01:2025-04 | K3: 1996-10:2025-04 | L3: 1983-01:2022-12 | M3: 1996-10:2025-04 | N3: 1986-12:2025-04 | O3: 1986-12:2025-04 | P3: 2003-12:2025-04 | Q3: 2006-03:2025-04 | R3: 2005-12:2025-04 | S3: 2002-01:2025-04 | T3: 2002-12:2025-04 | U3: 1990-01:2025-03 | V3: 2011-02:2025-03 | W3: 2011-01:2025-03 | X3: 1985-12:2025-04 | Y3: 1985-12:2025-04 | Z3: 2005-01:2025-04 | AA3: 2005-01:2025-04
A4: 更新时间 | B4: 2025-04-16 | C4: 2025-05-06 | D4: 2025-05-06 | E4: 2025-02-05 | F4: 2025-04-30 | G4: 2025-04-30 | H4: 2025-04-16 | I4: 2025-04-16 | J4: 2025-05-10 | K4: 2025-05-10 | L4: 2023-01-16 | M4: 2025-05-10 | N4: 2025-05-14 | O4: 2025-05-14 | P4: 2025-05-14 | Q4: 2025-05-14 | R4: 2025-05-14 | S4: 2025-05-14 | T4: 2025-05-14 | U4: 2025-04-16 | V4: 2025-04-16 | W4: 2025-04-17 | X4: 2025-05-14 | Y4: 2025-05-14 | Z4: 2025-04-30 | AA4: 2025-04-30
A5: 36922 | B5: 0 | C5: 0 | D5: 0 | E5: 96.39 | F5: 0 | G5: 0 | H5: 12.5 | I5: 0 | J5: 1.2 | K5: 1.43 | L5: -0.5 | M5: 3.6 | N5: 16.8 | O5: 15.16 | P5: 0 | Q5: 0 | R5: 0 | S5: 0 | T5: 0 | U5: 2.3 | V5: 0 | W5: 0 | X5: 54406 | Y5: 137543.63 | Z5: 0 | AA5: 0
A6: 36950 | B6: 0 | C6: 0 | D6: 0 | E6: 96.83 | F6: 0 | G6: 0 | H6: 8.6 | I6: 0 | J6: 0 | K6: 0.9 | L6: -1.7 | M6: 2.7 | N6: 16.4 | O6: 15.2 | P6: 0 | Q6: 0 | R6: 0 | S6: 0 | T6: 0 | U6: 19 | V6: 0 | W6: 0 | X6: 51998 | Y6: 136210.17 | Z6: 0 | AA6: 0
A7: 36981 | B7: 9.5 | C7: 0 | D7: 0 | E7: 97.49 | F7: 0 | G7: 0 | H7: 9.5 | I7: 3.1262 | J7: 0.8 | K7: 0.2 | L7: -0.9 | M7: 2.1 | N7: 17.4 | O7: 14.83 | P7: 0 | Q7: 0 | R7: 0 | S7: 0 | T7: 0 | U7: 12.1 | V7: 0 | W7: 0 | X7: 53033 | Y7: 138744.46 | Z7: 0 | AA7: 0
A8: 37011 | B8: 0 | C8: 0 | D8: 0 | E8: 96.63 | F8: 0 | G8: 0 | H8: 9.7 | I8: 0 | J8: 1.6 | K8: -0.1 | L8: 0.1 | M8: 1 | N8: 15 | O8: 13.94 | P8: 0 | Q8: 0 | R8: 0 | S8: 0 | T8: 0 | U8: 11.5 | V8: 0 | W8: 0 | X8: 53261 | Y8: 139949.85 | Z8: 0 | AA8: 0
A9: 37042 | B9: 0 | C9: 0 | D9: 0 | E9: 96.28 | F9: 0 | G9: 0 | H9: 11.1 | I9: 0 | J9: 1.7 | K9: -0.2 | L9: 0.1 | M9: 1.1 | N9: 14.9 | O9: 14.48 | P9: 0 | Q9: 0 | R9: 0 | S9: 0 | T9: 0 | U9: 10.2 | V9: 0 | W9: 0 | X9: 53423 | Y9: 139015.84 | Z9: 0 | AA9: 0
A10: 37072 | B10: 8.6 | C10: 0 | D10: 0 | E10: 95.78 | F10: 0 | G10: 0 | H10: 10 | I10: 2.3571 | J10: 1.4 | K10: -0.6 | L10: -0.1 | M10: 0.5 | N10: 14.9 | O10: 14.3 | P10: 0 | Q10: 0 | R10: 0 | S10: 0 | T10: 0 | U10: 10.1 | V10: 0 | W10: 0 | X10: 55187 | Y10: 147809.67 | Z10: 0 | AA10: 0
A11: 37103 | B11: 0 | C11: 0 | D11: 0 | E11: 95.24 | F11: 0 | G11: 0 | H11: 9.8 | I11: 0 | J11: 1.5 | K11: -1.3 | L11: -0.2 | M11: -0.4 | N11: 11.9 | O11: 13.5 | P11: 0 | Q11: 0 | R11: 0 | S11: 0 | T11: 0 | U11: 8.1 | V11: 0 | W11: 0 | X11: 53503 | Y11: 149228.73 | Z11: 0 | AA11: 0
A12: 37134 | B12: 0 | C12: 0 | D12: 0 | E12: 95.11 | F12: 0 | G12: 0 | H12: 9.6 | I12: 0 | J12: 1 | K12: -2 | L12: -1.2 | M12: -1.3 | N12: 14.2 | O12: 13.6 | P12: 0 | Q12: 0 | R12: 0 | S12: 0 | T12: 0 | U12: 8.1 | V12: 0 | W12: 0 | X12: 55809 | Y12: 149941.76 | Z12: 0 | AA12: 0
A13: 37164 | B13: 8 | C13: 0 | D13: 0 | E13: 94.97 | F13: 0 | G13: 0 | H13: 9.9 | I13: 2.0303 | J13: -0.1 | K13: -2.9 | L13: -1.3 | M13: -1.8 | N13: 12.3 | O13: 13.6 | P13: 0 | Q13: 0 | R13: 0 | S13: 0 | T13: 0 | U13: 9.5 | V13: 0 | W13: 0 | X13: 56823 | Y13: 151642.64 | Z13: 0 | AA13: 0
A14: 37195 | B14: 0 | C14: 0 | D14: 0 | E14: 95.01 | F14: 0 | G14: 0 | H14: 10.5 | I14: 0 | J14: 0.2 | K14: -3.1 | L14: -0.8 | M14: -2.5 | N14: 12.3 | O14: 12.9 | P14: 0 | Q14: 0 | R14: 0 | S14: 0 | T14: 0 | U14: 8.8 | V14: 0 | W14: 0 | X14: 56115 | Y14: 151497.25 | Z14: 0 | AA14: 0
A15: 37225 | B15: 0 | C15: 0 | D15: 0 | E15: 94.95 | F15: 0 | G15: 0 | H15: 10.1 | I15: 0 | J15: -0.3 | K15: -3.7 | L15: -1.7 | M15: -3.5 | N15: 11.4 | O15: 13.2 | P15: 0 | Q15: 0 | R15: 0 | S15: 0 | T15: 0 | U15: 7.9 | V15: 0 | W15: 0 | X15: 56580 | Y15: 154088.33 | Z15: 0 | AA15: 0
A16: 37256 | B16: 7.5 | C16: 0 | D16: 0 | E16: 95.23 | F16: 0 | G16: 0 | H16: 9.6 | I16: 1.0608 | J16: -0.3 | K16: -4 | L16: -1.8 | M16: -4.1 | N16: 12.7 | O16: 14.4 | P16: 0 | Q16: 0 | R16: 0 | S16: 0 | T16: 0 | U16: 8.7 | V16: 0 | W16: 0 | X16: 59871.59 | Y16: 158301.92 | Z16: 0 | AA16: 0
... A296: 45777 | B296: 0 | C296: 88.231556 | D296: 0 | E296: 0 | F296: 1.9 | G296: 44.9 | H296: 0 | I296: 0 | J296: -0.1 | K296: -2.7 | L296: 0 | M296: -2.7 | N296: 1.5 | O296: 8 | P296: 8.7 | Q296: 7.370392 | R296: 8.4550367 | S296: 163362 | T296: 424 | U296: 0 | V296: 0 | W296: 0 | X296: 1091407.3 | Y296: 3251739.3 | Z296: 49.2 | AA296: 47.3

Sheet INFO
C2: macroEcoIdx | D2: cycType | E2: inModel | F2: abbr | G2: combine | H2: deflator | I2: alternative | J2: beg | K2: update
C3: GDP:不变价:当季同比 | D3: 1 | E3: TRUE | F3: GDP | G3: FALSE | H3: FALSE | I3: FALSE | J3: =EOMONTH(DATE(LEFT(OFFSET(EDB!$A$3,0,MATCH($C3,EDB!$B$2:$AZ$2,0)),4),MID(OFFSET(EDB!$A$3,0,MATCH($C3,EDB!$B$2:$AZ$2,0)),6,2),1),0) -> 33694 | K3: =OFFSET(EDB!$A$4,0,MATCH($C3,EDB!$B$2:$AZ$2,0)) -> 2025-04-16
C4: 中金CMI指数:初值 | D4: 1 | E4: TRUE | F4: CMIB | G4: TRUE | H4: FALSE | I4: FALSE | J4: =EOMONTH(DATE(LEFT(OFFSET(EDB!$A$3,0,MATCH($C4,EDB!$B$2:$AZ$2,0)),4),MID(OFFSET(EDB!$A$3,0,MATCH($C4,EDB!$B$2:$AZ$2,0)),6,2),1),0) -> 39844 | K4: =OFFSET(EDB!$A$4,0,MATCH($C4,EDB!$B$2:$AZ$2,0)) -> 2025-05-06
C5: 中金CMI指数:终值 | D5: 1 | E5: TRUE | F5: CMIE | G5: TRUE | H5: FALSE | I5: FALSE | J5: =EOMONTH(DATE(LEFT(OFFSET(EDB!$A$3,0,MATCH($C5,EDB!$B$2:$AZ$2,0)),4),MID(OFFSET(EDB!$A$3,0,MATCH($C5,EDB!$B$2:$AZ$2,0)),6,2),1),0) -> 39844 | K5: =OFFSET(EDB!$A$4,0,MATCH($C5,EDB!$B$2:$AZ$2,0)) -> 2025-05-06
C6: 宏观经济景气指数:一致指数 | D6: 1 | E6: TRUE | F6: ECI | G6: FALSE | H6: FALSE | I6: TRUE | J6: =EOMONTH(DATE(LEFT(OFFSET(EDB!$A$3,0,MATCH($C6,EDB!$B$2:$AZ$2,0)),4),MID(OFFSET(EDB!$A$3,0,MATCH($C6,EDB!$B$2:$AZ$2,0)),6,2),1),0) -> 33269 | K6: =OFFSET(EDB!$A$4,0,MATCH($C6,EDB!$B$2:$AZ$2,0)) -> 2025-02-05
C7: PMI:新订单-产成品库存 | D7: 1 | E7: TRUE | F7: PMI | G7: FALSE | H7: FALSE | I7: FALSE | J7: =EOMONTH(DATE(LEFT(OFFSET(EDB!$A$3,0,MATCH($C7,EDB!$B$2:$AZ$2,0)),4),MID(OFFSET(EDB!$A$3,0,MATCH($C7,EDB!$B$2:$AZ$2,0)),6,2),1),0) -> 38383 | K7: =OFFSET(EDB!$A$4,0,MATCH($C7,EDB!$B$2:$AZ$2,0)) -> 2025-04-30
C8: PMI:新订单 | D8: 1 | E8: FALSE | F8: NA | G8: FALSE | H8: FALSE | I8: FALSE | J8: =EOMONTH(DATE(LEFT(OFFSET(EDB!$A$3,0,MATCH($C8,EDB!$B$2:$AZ$2,0)),4),MID(OFFSET(EDB!$A$3,0,MATCH($C8,EDB!$B$2:$AZ$2,0)),6,2),1),0) -> 38383 | K8: =OFFSET(EDB!$A$4,0,MATCH($C8,EDB!$B$2:$AZ$2,0)) -> 2025-04-30
C9: PMI:产成品库存 | D9: 1 | E9: FALSE | F9: NA | G9: FALSE | H9: FALSE | I9: FALSE | J9: =EOMONTH(DATE(LEFT(OFFSET(EDB!$A$3,0,MATCH($C9,EDB!$B$2:$AZ$2,0)),4),MID(OFFSET(EDB!$A$3,0,MATCH($C9,EDB!$B$2:$AZ$2,0)),6,2),1),0) -> 38383 | K9: =OFFSET(EDB!$A$4,0,MATCH($C9,EDB!$B$2:$AZ$2,0)) -> 2025-04-30
C10: 非制造业PMI:新订单 | D10: 1 | E10: TRUE | F10: PMIN | G10: FALSE | H10: FALSE | I10: FALSE | J10: =EOMONTH(DATE(LEFT(OFFSET(EDB!$A$3,0,MATCH($C10,EDB!$B$2:$AZ$2,0)),4),MID(OFFSET(EDB!$A$3,0,MATCH($C10,EDB!$B$2:$AZ$2,0)),6,2),1),0) -> 39113 | K10: =OFFSET(EDB!$A$4,0,MATCH($C10,EDB!$B$2:$AZ$2,0)) -> 2025-04-30
C11: 社会消费品零售总额:当月同比 | D11: 1 | E11: TRUE | F11: CONS | G11: FALSE | H11: TRUE | I11: TRUE | J11: =EOMONTH(DATE(LEFT(OFFSET(EDB!$A$3,0,MATCH($C11,EDB!$B$2:$AZ$2,0)),4),MID(OFFSET(EDB!$A$3,0,MATCH($C11,EDB!$B$2:$AZ$2,0)),6,2),1),0) -> 34730 | K11: =OFFSET(EDB!$A$4,0,MATCH($C11,EDB!$B$2:$AZ$2,0)) -> 2025-04-16
C12: GDP:平减指数:GDP:初步核算:当季同比 | D12: 1 | E12: TRUE | F12: PRICE | G12: FALSE | H12: FALSE | I12: FALSE | J12: =EOMONTH(DATE(LEFT(OFFSET(EDB!$A$3,0,MATCH($C12,EDB!$B$2:$AZ$2,0)),4),MID(OFFSET(EDB!$A$3,0,MATCH($C12,EDB!$B$2:$AZ$2,0)),6,2),1),0) -> 34059 | K12: =OFFSET(EDB!$A$4,0,MATCH($C12,EDB!$B$2:$AZ$2,0)) -> 2025-04-16
C13: 工业增加值:当月同比 | D13: 1 | E13: TRUE | F13: IND | G13: FALSE | H13: TRUE | I13: TRUE | J13: =EOMONTH(DATE(LEFT(OFFSET(EDB!$A$3,0,MATCH($C13,EDB!$B$2:$AZ$2,0)),4),MID(OFFSET(EDB!$A$3,0,MATCH($C13,EDB!$B$2:$AZ$2,0)),6,2),1),0) -> 32904 | K13: =OFFSET(EDB!$A$4,0,MATCH($C13,EDB!$B$2:$AZ$2,0)) -> 2025-04-16
C14: 工业增加值:环比:季调 | D14: 1 | E14: FALSE | F14: NA | G14: FALSE | H14: FALSE | I14: FALSE | J14: =EOMONTH(DATE(LEFT(OFFSET(EDB!$A$3,0,MATCH($C14,EDB!$B$2:$AZ$2,0)),4),MID(OFFSET(EDB!$A$3,0,MATCH($C14,EDB!$B$2:$AZ$2,0)),6,2),1),0) -> 40602 | K14: =OFFSET(EDB!$A$4,0,MATCH($C14,EDB!$B$2:$AZ$2,0)) -> 2025-04-16
... C28: M2 | D28: 3 | E28: FALSE | F28: NA | G28: FALSE | H28: FALSE | I28: FALSE | J28: =EOMONTH(DATE(LEFT(OFFSET(EDB!$A$3,0,MATCH($C28,EDB!$B$2:$AZ$2,0)),4),MID(OFFSET(EDB!$A$3,0,MATCH($C28,EDB!$B$2:$AZ$2,0)),6,2),1),0) -> 31412 | K28: =OFFSET(EDB!$A$4,0,MATCH($C28,EDB!$B$2:$AZ$2,0)) -> 2025-05-14
